Metadata-Version: 2.1
Name: odoo13-addon-website-oca-integrator
Version: 13.0.1.0.1.dev2
Summary: Displays Integrators in website.
Home-page: https://github.com/OCA/oca-custom
Author: Odoo Community Association (OCA), Surekha Technologies
Author-email: support@odoo-community.org
License: AGPL-3
Platform: UNKNOWN
Classifier: Programming Language :: Python
Classifier: Framework :: Odoo
Classifier: Framework :: Odoo :: 13.0
Classifier: License :: OSI Approved :: GNU Affero General Public License v3
Requires-Python: >=3.5
Requires-Dist: odoo13-addon-apps-product-creator
Requires-Dist: odoo <13.1dev,>=13.0a
